Workbook

Sheet Key Assumptions RJPP
A1: Key Assumptions RJPP 2026-2030 PT ABC Energy
A2: Parameter | B2: Year 2026 | C2: Year 2027 | D2: Year 2028 | E2: Year 2029 | F2: Year 2030
A3: Oil Price (USD/bbl) | B3: 70 | C3: 75 | D3: 80 | E3: 85 | F3: 90
A4: Natural Gas Price (USD/MMSBtu) | B4: 2.8 | C4: 2.85 | D4: 2.9 | E4: 2.95 | F4: 3
A5: Natural Gas Price (USD/MMScf) | B5: =B4*1000 -> 2800 | C5: =C4*1000 -> 2850 | D5: =D4*1000 -> 2900 | E5: =E4*1000 -> 2950 | F5: =F4*1000 -> 3000
A6: Kurs USD/IDR | B6: 16500 | C6: 17000 | D6: 17500 | E6: 18000 | F6: 18500

Sheet Operasional
A2: Produksi Minyak & Gas
A3: PRODUKSI MINYAK (MBOPD) | B3: Year 2026 | C3: Year 2027 | D3: Year 2028 | E3: Year 2029 | F3: Year 2030
A5: Produksi Domestik | B5: 225 | C5: 215 | D5: 205 | E5: 190 | F5: 185
A6: Produksi Internasional | B6: 90 | C6: 95 | D6: 100 | E6: 105 | F6: 110
A7: Produksi dari M&A | B7: 0 | C7: 40 | D7: 70 | E7: 100 | F7: 150
A8: Total Produksi Minyak (MBOPD) | B8: =SUM(B5:B7) -> 315 | C8: =SUM(C5:C7) -> 350 | D8: =SUM(D5:D7) -> 375 | E8: =SUM(E5:E7) -> 395 | F8: =SUM(F5:F7) -> 445
A10: PRODUKSI GAS (MMSCFD) | B10: Year 2026 | C10: Year 2027 | D10: Year 2028 | E10: Year 2029 | F10: Year 2030
A11: Produksi Domestik | B11: 575 | C11: 625 | D11: 700 | E11: 750 | F11: 775
A12: Produksi Internasional | B12: 220 | C12: 230 | D12: 250 | E12: 275 | F12: 300
A13: Produksi dari M&A | B13: 0 | C13: 57 | D13: 150 | E13: 200 | F13: 250
A14: Total Produksi Gas (MMSCFD) | B14: =SUM(B11:B13) -> 795 | C14: =SUM(C11:C13) -> 912 | D14: =SUM(D11:D13) -> 1100 | E14: =SUM(E11:E13) -> 1225 | F14: =SUM(F11:F13) -> 1325

Sheet Finansial
C7: Alternative Forecasting Methods
B10: ='[1]Model-R'!O10 -> 1 | C10: Alternative: Regression, Bottom Up, Top Down
B11: ='[1]Model-R'!O11 -> 1 | C11: Alternative: COGS Margin, Cost per Unit
B12: ='[1]Model-R'!O12 -> 1
B13: ='[1]Model-R'!O13 -> 1 | C13: Alternative: Percent of Sales
B14: ='[1]Model-R'!O14 -> 1
B15: ='[1]Model-R'!O15 -> 1 | C15: Alternative: Depreciation Percent of PP&E
B16: ='[1]Model-R'!O16 -> 1 | C16: Alternative: Beginning Debt
B17: ='[1]Model-R'!O17 -> 1
B20: ='[1]Model-R'!O20 -> 1 | C20: Alternative: Capex $, Capex % of Sales
B21: ='[1]Model-R'!O21 -> 1 | C21: Alternative: Use Average Balance of Receivables
B22: ='[1]Model-R'!O22 -> 1 | C22: Alternative: Use Average Balance of Inventory
B23: ='[1]Model-R'!O23 -> 1 | C23: Alternative: Use Average Balance of Payables
B24: ='[1]Model-R'!O24 -> 1 | C24: Alternative: Use Average Balance of Income Tax Payable
B25: ='[1]Model-R'!O25 -> 1 | C25: Alternative: Debt/Equity Ratio
B26: ='[1]Model-R'!O26 -> 1 | C26: Alternative: Debt/Equity Ratio
B27: ='[1]Model-R'!O27 -> 1
B31: Income Statement
B33: All figures in USD thousands unless stated | D33: Year 2026 | E33: Year 2027 | F33: Year 2028 | G33: Year 2029 | H33: Year 2030
B35: Revenues | D35: =Operasional!B8*365*'Key Assumptions RJPP'!B3+Operasional!B14*365*'Key Assumptions RJPP'!B5/1000 -> 8860740 | E35: =Operasional!C8*365*'Key Assumptions RJPP'!C3+Operasional!C14*365*'Key Assumptions RJPP'!C5/1000 -> 10529958 | F35: =Operasional!D8*365*'Key Assumptions RJPP'!D3+Operasional!D14*365*'Key Assumptions RJPP'!D5/1000 -> 12114350 | G35: =Operasional!E8*365*'Key Assumptions RJPP'!E3+Operasional!E14*365*'Key Assumptions RJPP'!E5/1000 -> 13573894 | H35: =Operasional!F8*365*'Key Assumptions RJPP'!F3+Operasional!F14*365*'Key Assumptions RJPP'!F5/1000 -> 16069125
B36: Cost of Goods Sold | D36: -4000000 | E36: -5000000 | F36: -6000000 | G36: -7000000 | H36: -8400000
B37: Gross Profit | D37: =SUM(D35:D36) -> 4860740 | E37: =SUM(E35:E36) -> 5529958 | F37: =SUM(F35:F36) -> 6114350 | G37: =SUM(G35:G36) -> 6573893.8 | H37: =SUM(H35:H36) -> 7669125
B39: SG&A | D39: -1350000 | E39: -1687500 | F39: -1968750 | G39: -2193750 | H39: -2475000
B40: EBITDA | D40: =SUM(D37:D39) -> 3510740 | E40: =SUM(E37:E39) -> 3842458 | F40: =SUM(F37:F39) -> 4145600 | G40: =SUM(G37:G39) -> 4380143.8 | H40: =SUM(H37:H39) -> 5194125
B42: DD&A | D42: -1000000 | E42: -1150000 | F42: -1300000 | G42: -1500000 | H42: -1750000
B43: EBIT (Operating Profit) | D43: =SUM(D40:D42) -> 2510740 | E43: =SUM(E40:E42) -> 2692458 | F43: =SUM(F40:F42) -> 2845600 | G43: =SUM(G40:G42) -> 2880143.8 | H43: =SUM(H40:H42) -> 3444125
B45: Interest Expense | D45: -150000 | E45: -175000 | F45: -200000 | G45: -225000 | H45: -250000
B46: Earnings Before Taxes | D46: =SUM(D43:D45) -> 2360740 | E46: =SUM(E43:E45) -> 2517458 | F46: =SUM(F43:F45) -> 2645600 | G46: =SUM(G43:G45) -> 2655143.8 | H46: =SUM(H43:H45) -> 3194125
B48: Taxes (22%) | D48: =-D46*22% -> -519362.8 | E48: =-E46*22% -> -553840.76 | F48: =-F46*22% -> -582032 | G48: =-G46*22% -> -584131.62 | H48: =-H46*22% -> -702707.5
B49: Net Income | D49: =SUM(D46:D48) -> 1841377.2 | E49: =SUM(E46:E48) -> 1963617.2 | F49: =SUM(F46:F48) -> 2063568 | G49: =SUM(G46:G48) -> 2071012.1 | H49: =SUM(H46:H48) -> 2491417.5
B51: Common Dividends | D51: 4312 | E51: 4209 | F51: 2930.9751 | G51: =#REF!*G49 -> #REF! | H51: =#REF!*H49 -> #REF! | I51: Alternative: Forecast Share Count and Dividends per Share
B55: Balance Sheet
B57: All figures in USD thousands unless stated | D57: =+#REF! -> #REF! | E57: =+#REF! -> #REF! | F57: =+#REF! -> #REF! | G57: =+#REF! -> #REF! | H57: =+#REF! -> #REF!
B59: ASSETS
B60: Cash
B61: Trade and Other Receivables | D61: 12685 | E61: 14074 | F61: 14721.209 | G61: =G133 -> #REF! | H61: =H133 -> #REF!
B62: Inventories | D62: 7168 | E62: 7691 | F62: 8036.3319 | G62: =G134 -> #REF! | H62: =H134 -> #REF!
B63: Total Current Assets | D63: =SUM(D60:D62) -> 19853 | E63: =SUM(E60:E62) -> 21765 | F63: =SUM(F60:F62) -> 22757.54 | G63: =SUM(G60:G62) -> #REF! | H63: =SUM(H60:H62) -> #REF!
B65: Property Plant and Equipment | D65: 19263 | E65: 20371 | F65: 21175 | G65: =G153 -> #REF! | H65: =H153 -> #REF!
B67: TOTAL ASSETS | D67: =SUM(D65,D63) -> 39116 | E67: =SUM(E65,E63) -> 42136 | F67: =SUM(F65,F63) -> 43932.54 | G67: =SUM(G65,G63) -> #REF! | H67: =SUM(H65,H63) -> #REF!
B69: LIABILITIES
B70: Trade and Other Payables | D70: 10001 | E70: 10504 | F70: 11077.106 | G70: =G135 -> #REF! | H70: =H135 -> #REF!
B71: Income Taxes Payable | D71: 1088 | E71: 894 | F71: 581 | G71: =G136 -> #REF! | H71: =H136 -> #REF!
B72: Total Current Liabilities | D72: =SUM(D70:D71) -> 11089 | E72: =SUM(E70:E71) -> 11398 | F72: =SUM(F70:F71) -> 11658.106 | G72: =SUM(G70:G71) -> #REF! | H72: =SUM(H70:H71) -> #REF!
B74: Long-Term Debt | D74: 20000 | E74: 20000 | F74: 20000 | G74: =#REF! -> #REF! | H74: =#REF! -> #REF!
B75: Total Liabilities | D75: =SUM(D72,D74) -> 31089 | E75: =SUM(E72,E74) -> 31398 | F75: =SUM(F72,F74) -> 31658.106 | G75: =SUM(G72,G74) -> #REF! | H75: =SUM(H72,H74) -> #REF!
B77: EQUITY
B78: Common Stock and Additional Paid-In Capital | D78: 7627 | E78: 7627 | F78: 7627 | G78: =G174 -> #REF! | H78: =H174 -> #REF!
B79: Retained Earnings | D79: 5689 | E79: 9029 | F79: 14806.218 | G79: =G183 -> #REF! | H79: =H183 -> #REF!
B80: Total Shareholders' Equity | D80: =SUM(D78:D79) -> 13316 | E80: =SUM(E78:E79) -> 16656 | F80: =SUM(F78:F79) -> 22433.218 | G80: =SUM(G78:G79) -> #REF! | H80: =SUM(H78:H79) -> #REF!
B82: Total Liabilities & Equity | D82: =SUM(D75,D80) -> 44405 | E82: =SUM(E75,E80) -> 48054 | F82: =SUM(F75,F80) -> 54091.324 | G82: =SUM(G75,G80) -> #REF! | H82: =SUM(H75,H80) -> #REF!
B84: Balance Sheet Check | D84: =D82=D67 -> FALSE | E84: =E82=E67 -> FALSE | F84: =F82=F67 -> FALSE | G84: =G82=G67 -> #REF! | H84: =H82=H67 -> #REF!
B88: Cash Flow Statement
B90: All figures in USD thousands unless stated | D90: =+#REF! -> #REF! | E90: =+#REF! -> #REF! | F90: =+#REF! -> #REF! | G90: =+#REF! -> #REF! | H90: =+#REF! -> #REF!
B92: Cash Flows from Operating Activities
B93: Net Income
B94: Depreciation
B95: Changes in Operating Assets and Liabilities:
B96: Trade and Other Receivables
B97: Inventories
B98: Trade and Other Payables
B99: Income Taxes Payable
B100: Cash Flows from Operating Activities
B102: Investing Activities
B103: Acquisitions of Property and Equipment | D103: -3005 | E103: -3911 | F103: -3710.8354
B104: Cash Flows from Investing Activities
B106: Financing Activities
B107: Issuance of Common Stock | D107: 0
B108: Dividends (current year)
B109: Increase/(Decrease) in Long-Term Debt | D109: 0
B110: Cash Flows from Financing Activities
B112: Cash and Equivalents, Beginning of the Year | D112: 5671
B113: Increase/(Decrease) in Cash and Equivalents
B114: Cash and Equivalents, End of the Year
B118: Working Capital and PP&E Schedule
B120: All figures in USD thousands unless stated | D120: =+#REF! -> #REF! | E120: =+#REF! -> #REF! | F120: =+#REF! -> #REF! | G120: =+#REF! -> #REF! | H120: =+#REF! -> #REF!
B122: Days in Period | D122: =#REF! -> #REF! | E122: =#REF! -> #REF! | F122: =#REF! -> #REF! | G122: =#REF! -> #REF! | H122: =#REF! -> #REF!
B123: Revenue | D123: =D35 -> 8860740 | E123: =E35 -> 10529958 | F123: =F35 -> 12114350 | G123: =G35 -> 13573894 | H123: =H35 -> 16069125
B124: Cost of Goods Sold | D124: =-D36 -> 4000000 | E124: =-E36 -> 5000000 | F124: =-F36 -> 6000000 | G124: =-G36 -> 7000000 | H124: =-H36 -> 8400000
B125: Taxes | D125: =-D48 -> 519362.8 | E125: =-E48 -> 553840.76 | F125: =-F48 -> 582032 | G125: =-G48 -> 584131.62 | H125: =-H48 -> 702707.5
B127: Trade and Other Receivables | C127: (Days) | D127: =#REF! -> #REF! | E127: =#REF! -> #REF! | F127: =#REF! -> #REF! | G127: =#REF! -> #REF! | H127: =#REF! -> #REF!
B128: Inventory | C128: (Days) | D128: =#REF! -> #REF! | E128: =#REF! -> #REF! | F128: =#REF! -> #REF! | G128: =#REF! -> #REF! | H128: =#REF! -> #REF!
B129: Trade and Other Payables | C129: (Days) | D129: =#REF! -> #REF! | E129: =#REF! -> #REF! | F129: =#REF! -> #REF! | G129: =#REF! -> #REF! | H129: =#REF! -> #REF!
B130: Income Tax Payable (Percent of Taxes) | D130: =#REF! -> #REF! | E130: =#REF! -> #REF! | F130: =#REF! -> #REF! | G130: =#REF! -> #REF! | H130: =#REF! -> #REF!
B132: Working Capital
B133: Trade and Other Receivables | D133: =D61 -> 12685 | E133: =E61 -> 14074 | F133: =F61 -> 14721.209 | G133: =G127/G122*G123 -> #REF! | H133: =H127/H122*H123 -> #REF!
B134: Inventory | D134: =D62 -> 7168 | E134: =E62 -> 7691 | F134: =F62 -> 8036.3319 | G134: =G128/G122*G124 -> #REF! | H134: =H128/H122*H124 -> #REF!
B135: Trade and Other Payables | D135: =D70 -> 10001 | E135: =E70 -> 10504 | F135: =F70 -> 11077.106 | G135: =G129/G122*G124 -> #REF! | H135: =H129/H122*H124 -> #REF!
B136: Income Tax Payable | D136: =D71 -> 1088 | E136: =E71 -> 894 | F136: =F71 -> 581 | G136: =G130*G125 -> #REF! | H136: =H130*H125 -> #REF!
B138: Cash Changes from Working Capital
B139: Trade and Other Receivables | D139: -1280 | E139: =D133-E133 -> -1389 | F139: =E133-F133 -> -647.20855 | G139: =F133-G133 -> #REF! | H139: =G133-H133 -> #REF!
B140: Inventory | D140: -470 | E140: =D134-E134 -> -523 | F140: =E134-F134 -> -345.33188 | G140: =F134-G134 -> #REF! | H140: =G134-H134 -> #REF!
B141: Trade and Other Payables | D141: 490 | E141: =E135-D135 -> 503 | F141: =F135-E135 -> 573.1061 | G141: =G135-F135 -> #REF! | H141: =H135-G135 -> #REF!
B142: Income Taxes Payable | D142: 50 | E142: =E136-D136 -> -194 | F142: =F136-E136 -> -313 | G142: =G136-F136 -> #REF! | H142: =H136-G136 -> #REF!
B143: Cash from Working Capital Items | D143: =SUM(D139:D142) -> -1210 | E143: =SUM(E139:E142) -> -1603 | F143: =SUM(F139:F142) -> -732.43432 | G143: =SUM(G139:G142) -> #REF! | H143: =SUM(H139:H142) -> #REF!
B145: Revenue | D145: =D123 -> 8860740 | E145: =E123 -> 10529958 | F145: =F123 -> 12114350 | G145: =G123 -> 13573894 | H145: =H123 -> 16069125
B146: Capital Asset Turnover Ratio | C146: (x) | D146: =#REF! -> #REF! | E146: =#REF! -> #REF! | F146: =#REF! -> #REF! | G146: =#REF! -> #REF! | H146: =#REF! -> #REF!
B147: Depreciation (Percent of Sales) | D147: =#REF! -> #REF! | E147: =#REF! -> #REF! | F147: =#REF! -> #REF! | G147: =#REF! -> #REF! | H147: =#REF! -> #REF!
B149: Property, Plant & Equipment (PP&E)
B150: Beginning of Period | D150: =D153-D152-D151 -> #REF! | E150: =D153 -> 19263 | F150: =E153 -> #REF! | G150: =F153 -> #REF! | H150: =G153 -> #REF!
...
