Workbook

Sheet Key Assumptions RJPP
A1: Key Assumptions RJPP 2026-2030 PT ABC Energy
A2: Parameter | B2: Year 2026 | C2: Year 2027 | D2: Year 2028 | E2: Year 2029 | F2: Year 2030
A3: Harga Listrik USD/kwH | B3: 0.08 | C3: 0.082 | D3: 0.085 | E3: 0.087 | F3: 0.09
A4: Kurs USD/IDR | B4: 16500 | C4: 17000 | D4: 17500 | E4: 18000 | F4: 18500

Sheet Operasional
A1: Volume Kapasitas Terpasang dan Produksi Listrik New Energy
A2: Kaspasitas Terpasang (MW) | B2: Year 2026 | C2: Year 2027 | D2: Year 2028 | E2: Year 2029 | F2: Year 2030
A3: Geothermal | B3: 880 | C3: 960 | D3: 1300 | E3: 1400 | F3: 1600
A4: PLTS | B4: 160 | C4: 280 | D4: 320 | E4: 480 | F4: 500
A5: PLTSa | B5: 50 | C5: 50 | D5: 50 | E5: 50 | F5: 50
A6: Total Kapasitas Terpasang (MW) | B6: =SUM(B3:B5) -> 1090 | C6: =SUM(C3:C5) -> 1290 | D6: =SUM(D3:D5) -> 1670 | E6: =SUM(E3:E5) -> 1930 | F6: =SUM(F3:F5) -> 2150
A8: Produksi Listrik (GWh) | B8: Year 2026 | C8: Year 2027 | D8: Year 2028 | E8: Year 2029 | F8: Year 2030
A9: Geothermal | B9: 5280 | C9: 5760 | D9: 9100 | E9: 9800 | F9: 11200
A10: PLTS | B10: 40 | C10: 70 | D10: 160 | E10: 240 | F10: 250
A11: Other New Energy | B11: 7 | C11: 42 | D11: 43 | E11: 44 | F11: 45
A12: Total Produksi Listrik (GWh) | B12: =SUM(B9:B11) -> 5327 | C12: =SUM(C9:C11) -> 5872 | D12: =SUM(D9:D11) -> 9303 | E12: =SUM(E9:E11) -> 10084 | F12: =SUM(F9:F11) -> 11495
A14: Total Produksi Listrik (kWh) | B14: =B12*1000000 -> 5327000000 | C14: =C12*1000000 -> 5872000000 | D14: =D12*1000000 -> 9303000000 | E14: =E12*1000000 -> 10084000000 | F14: =F12*1000000 -> 11495000000

Sheet Finansial
A1: Income Statement
A3: All figures in USD thousands unless stated | C3: Year 2026 | D3: Year 2027 | E3: Year 2028 | F3: Year 2029 | G3: Year 2030
A5: Revenues | C5: =(Operasional!B14*'Key Assumptions RJPP'!B3)/1000 -> 426160 | D5: =(Operasional!C14*'Key Assumptions RJPP'!C3)/1000 -> 481504 | E5: =(Operasional!D14*'Key Assumptions RJPP'!D3)/1000 -> 790755 | F5: =(Operasional!E14*'Key Assumptions RJPP'!E3)/1000 -> 877308 | G5: =(Operasional!F14*'Key Assumptions RJPP'!F3)/1000 -> 1034550
A6: Cost of Goods Sold | C6: -191772 | D6: -211862 | E6: -332117 | F6: -359696 | G6: -413820
A7: Gross Profit | C7: =SUM(C5:C6) -> 234388 | D7: =SUM(D5:D6) -> 269642 | E7: =SUM(E5:E6) -> 458638 | F7: =SUM(F5:F6) -> 517612 | G7: =SUM(G5:G6) -> 620730
A9: SG&A | C9: -34093 | D9: -38520 | E9: -63260 | F9: -70185 | G9: -82764
A10: EBITDA | C10: =SUM(C7:C9) -> 200295 | D10: =SUM(D7:D9) -> 231122 | E10: =SUM(E7:E9) -> 395378 | F10: =SUM(F7:F9) -> 447427 | G10: =SUM(G7:G9) -> 537966
A12: DD&A | C12: -42616 | D12: -48150 | E12: -79076 | F12: -87731 | G12: -103455
A13: EBIT (Operating Profit) | C13: =SUM(C10:C12) -> 157679 | D13: =SUM(D10:D12) -> 182972 | E13: =SUM(E10:E12) -> 316302 | F13: =SUM(F10:F12) -> 359696 | G13: =SUM(G10:G12) -> 434511
A15: Interest Expense | C15: -12000 | D15: -12000 | E15: -12000 | F15: -12000 | G15: -12000
A16: Earnings Before Taxes | C16: =SUM(C13:C15) -> 145679 | D16: =SUM(D13:D15) -> 170972 | E16: =SUM(E13:E15) -> 304302 | F16: =SUM(F13:F15) -> 347696 | G16: =SUM(G13:G15) -> 422511
A18: Taxes (22%) | C18: =-(0.22*C16) -> -32049.38 | D18: =-(0.22*D16) -> -37613.84 | E18: =-(0.22*E16) -> -66946.44 | F18: =-(0.22*F16) -> -76493.12 | G18: =-(0.22*G16) -> -92952.42
A19: Net Income | C19: =SUM(C16:C18) -> 113629.62 | D19: =SUM(D16:D18) -> 133358.16 | E19: =SUM(E16:E18) -> 237355.56 | F19: =SUM(F16:F18) -> 271202.88 | G19: =SUM(G16:G18) -> 329558.58
A21: Common Dividends | C21: 4312 | D21: 4209 | E21: 2930.9751 | F21: =#REF!*F19 -> #REF! | G21: =#REF!*G19 -> #REF! | I21: Alternative: Forecast Share Count and Dividends per Share
A25: Balance Sheet
A27: All figures in USD thousands unless stated | C27: =+#REF! -> #REF! | D27: =+#REF! -> #REF! | E27: =+#REF! -> #REF! | F27: =+#REF! -> #REF! | G27: =+#REF! -> #REF!
A29: ASSETS
A30: Cash
A31: Trade and Other Receivables | C31: 12685 | D31: 14074 | E31: 14721.209 | F31: =F103 -> #REF! | G31: =G103 -> #REF!
A32: Inventories | C32: 7168 | D32: 7691 | E32: 8036.3319 | F32: =F104 -> #REF! | G32: =G104 -> #REF!
A33: Total Current Assets | C33: =SUM(C30:C32) -> 19853 | D33: =SUM(D30:D32) -> 21765 | E33: =SUM(E30:E32) -> 22757.54 | F33: =SUM(F30:F32) -> #REF! | G33: =SUM(G30:G32) -> #REF!
A35: Property Plant and Equipment | C35: 19263 | D35: 20371 | E35: 21175 | F35: =F123 -> #REF! | G35: =G123 -> #REF!
A37: TOTAL ASSETS | C37: =SUM(C35,C33) -> 39116 | D37: =SUM(D35,D33) -> 42136 | E37: =SUM(E35,E33) -> 43932.54 | F37: =SUM(F35,F33) -> #REF! | G37: =SUM(G35,G33) -> #REF!
A39: LIABILITIES
A40: Trade and Other Payables | C40: 10001 | D40: 10504 | E40: 11077.106 | F40: =F105 -> #REF! | G40: =G105 -> #REF!
A41: Income Taxes Payable | C41: 1088 | D41: 894 | E41: 581 | F41: =F106 -> #REF! | G41: =G106 -> #REF!
A42: Total Current Liabilities | C42: =SUM(C40:C41) -> 11089 | D42: =SUM(D40:D41) -> 11398 | E42: =SUM(E40:E41) -> 11658.106 | F42: =SUM(F40:F41) -> #REF! | G42: =SUM(G40:G41) -> #REF!
A44: Long-Term Debt | C44: 20000 | D44: 20000 | E44: 20000 | F44: =#REF! -> #REF! | G44: =#REF! -> #REF!
A45: Total Liabilities | C45: =SUM(C42,C44) -> 31089 | D45: =SUM(D42,D44) -> 31398 | E45: =SUM(E42,E44) -> 31658.106 | F45: =SUM(F42,F44) -> #REF! | G45: =SUM(G42,G44) -> #REF!
A47: EQUITY
A48: Common Stock and Additional Paid-In Capital | C48: 7627 | D48: 7627 | E48: 7627 | F48: =F144 -> #REF! | G48: =G144 -> #REF!
A49: Retained Earnings | C49: 5689 | D49: 9029 | E49: 14806.218 | F49: =F153 -> #REF! | G49: =G153 -> #REF!
A50: Total Shareholders' Equity | C50: =SUM(C48:C49) -> 13316 | D50: =SUM(D48:D49) -> 16656 | E50: =SUM(E48:E49) -> 22433.218 | F50: =SUM(F48:F49) -> #REF! | G50: =SUM(G48:G49) -> #REF!
A52: Total Liabilities & Equity | C52: =SUM(C45,C50) -> 44405 | D52: =SUM(D45,D50) -> 48054 | E52: =SUM(E45,E50) -> 54091.324 | F52: =SUM(F45,F50) -> #REF! | G52: =SUM(G45,G50) -> #REF!
A54: Balance Sheet Check | C54: =C52=C37 -> FALSE | D54: =D52=D37 -> FALSE | E54: =E52=E37 -> FALSE | F54: =F52=F37 -> #REF! | G54: =G52=G37 -> #REF!
A58: Cash Flow Statement
A60: All figures in USD thousands unless stated | C60: =+#REF! -> #REF! | D60: =+#REF! -> #REF! | E60: =+#REF! -> #REF! | F60: =+#REF! -> #REF! | G60: =+#REF! -> #REF!
A62: Cash Flows from Operating Activities
A63: Net Income
A64: Depreciation
A65: Changes in Operating Assets and Liabilities:
A66: Trade and Other Receivables
A67: Inventories
A68: Trade and Other Payables
A69: Income Taxes Payable
A70: Cash Flows from Operating Activities
A72: Investing Activities
A73: Acquisitions of Property and Equipment | C73: -3005 | D73: -3911 | E73: -3710.8354
A74: Cash Flows from Investing Activities
A76: Financing Activities
A77: Issuance of Common Stock | C77: 0
A78: Dividends (current year)
A79: Increase/(Decrease) in Long-Term Debt | C79: 0
A80: Cash Flows from Financing Activities
A82: Cash and Equivalents, Beginning of the Year | C82: 5671
A83: Increase/(Decrease) in Cash and Equivalents
A84: Cash and Equivalents, End of the Year
A88: Working Capital and PP&E Schedule
A90: All figures in USD thousands unless stated | C90: =+#REF! -> #REF! | D90: =+#REF! -> #REF! | E90: =+#REF! -> #REF! | F90: =+#REF! -> #REF! | G90: =+#REF! -> #REF!
A92: Days in Period | C92: =#REF! -> #REF! | D92: =#REF! -> #REF! | E92: =#REF! -> #REF! | F92: =#REF! -> #REF! | G92: =#REF! -> #REF!
A93: Revenue | C93: =C5 -> 426160 | D93: =D5 -> 481504 | E93: =E5 -> 790755 | F93: =F5 -> 877308 | G93: =G5 -> 1034550
A94: Cost of Goods Sold | C94: =-C6 -> 191772 | D94: =-D6 -> 211862 | E94: =-E6 -> 332117 | F94: =-F6 -> 359696 | G94: =-G6 -> 413820
A95: Taxes | C95: =-C18 -> 32049.38 | D95: =-D18 -> 37613.84 | E95: =-E18 -> 66946.44 | F95: =-F18 -> 76493.12 | G95: =-G18 -> 92952.42
A97: Trade and Other Receivables | B97: (Days) | C97: =#REF! -> #REF! | D97: =#REF! -> #REF! | E97: =#REF! -> #REF! | F97: =#REF! -> #REF! | G97: =#REF! -> #REF!
A98: Inventory | B98: (Days) | C98: =#REF! -> #REF! | D98: =#REF! -> #REF! | E98: =#REF! -> #REF! | F98: =#REF! -> #REF! | G98: =#REF! -> #REF!
A99: Trade and Other Payables | B99: (Days) | C99: =#REF! -> #REF! | D99: =#REF! -> #REF! | E99: =#REF! -> #REF! | F99: =#REF! -> #REF! | G99: =#REF! -> #REF!
A100: Income Tax Payable (Percent of Taxes) | C100: =#REF! -> #REF! | D100: =#REF! -> #REF! | E100: =#REF! -> #REF! | F100: =#REF! -> #REF! | G100: =#REF! -> #REF!
A102: Working Capital
A103: Trade and Other Receivables | C103: =C31 -> 12685 | D103: =D31 -> 14074 | E103: =E31 -> 14721.209 | F103: =F97/F92*F93 -> #REF! | G103: =G97/G92*G93 -> #REF!
A104: Inventory | C104: =C32 -> 7168 | D104: =D32 -> 7691 | E104: =E32 -> 8036.3319 | F104: =F98/F92*F94 -> #REF! | G104: =G98/G92*G94 -> #REF!
A105: Trade and Other Payables | C105: =C40 -> 10001 | D105: =D40 -> 10504 | E105: =E40 -> 11077.106 | F105: =F99/F92*F94 -> #REF! | G105: =G99/G92*G94 -> #REF!
A106: Income Tax Payable | C106: =C41 -> 1088 | D106: =D41 -> 894 | E106: =E41 -> 581 | F106: =F100*F95 -> #REF! | G106: =G100*G95 -> #REF!
A108: Cash Changes from Working Capital
A109: Trade and Other Receivables | C109: -1280 | D109: =C103-D103 -> -1389 | E109: =D103-E103 -> -647.20855 | F109: =E103-F103 -> #REF! | G109: =F103-G103 -> #REF!
A110: Inventory | C110: -470 | D110: =C104-D104 -> -523 | E110: =D104-E104 -> -345.33188 | F110: =E104-F104 -> #REF! | G110: =F104-G104 -> #REF!
A111: Trade and Other Payables | C111: 490 | D111: =D105-C105 -> 503 | E111: =E105-D105 -> 573.1061 | F111: =F105-E105 -> #REF! | G111: =G105-F105 -> #REF!
A112: Income Taxes Payable | C112: 50 | D112: =D106-C106 -> -194 | E112: =E106-D106 -> -313 | F112: =F106-E106 -> #REF! | G112: =G106-F106 -> #REF!
A113: Cash from Working Capital Items | C113: =SUM(C109:C112) -> -1210 | D113: =SUM(D109:D112) -> -1603 | E113: =SUM(E109:E112) -> -732.43432 | F113: =SUM(F109:F112) -> #REF! | G113: =SUM(G109:G112) -> #REF!
A115: Revenue | C115: =C93 -> 426160 | D115: =D93 -> 481504 | E115: =E93 -> 790755 | F115: =F93 -> 877308 | G115: =G93 -> 1034550
A116: Capital Asset Turnover Ratio | B116: (x) | C116: =#REF! -> #REF! | D116: =#REF! -> #REF! | E116: =#REF! -> #REF! | F116: =#REF! -> #REF! | G116: =#REF! -> #REF!
A117: Depreciation (Percent of Sales) | C117: =#REF! -> #REF! | D117: =#REF! -> #REF! | E117: =#REF! -> #REF! | F117: =#REF! -> #REF! | G117: =#REF! -> #REF!
A119: Property, Plant & Equipment (PP&E)
A120: Beginning of Period | C120: =C123-C122-C121 -> #REF! | D120: =C123 -> 19263 | E120: =D123 -> #REF! | F120: =E123 -> #REF! | G120: =F123 -> #REF!
A121: Capital Expenditures/Additions (Disposals) | C121: =-C73 -> 3005 | D121: =-D73 -> 3911 | E121: =-E73 -> 3710.8354 | F121: =F123-F122-F120 -> #REF! | G121: =G123-G122-G120 -> #REF!
A122: Depreciation Expense | C122: =#REF! -> #REF! | D122: =#REF! -> #REF! | E122: =#REF! -> #REF! | F122: =-F117*F115 -> #REF! | G122: =-G117*G115 -> #REF!
A123: Net PP&E, End of Period | C123: =C35 -> 19263 | D123: =SUM(D120:D122) -> #REF! | E123: =SUM(E120:E122) -> #REF! | F123: =F115/F116 -> #REF! | G123: =G115/G116 -> #REF!
A126: Capital Structure Schedules
A128: All figures in USD thousands unless stated | C128: =+#REF! -> #REF! | D128: =+#REF! -> #REF! | E128: =+#REF! -> #REF! | F128: =+#REF! -> #REF! | G128: =+#REF! -> #REF!
A131: Long Term Debt (LTD)
A132: Beginning of Period | C132: =C134-C133 -> #REF! | D132: =C134 -> #REF! | E132: =D134 -> #REF! | F132: =E134 -> #REF! | G132: =F134 -> #REF!
A133: Additions (Repayments) | C133: =C79 -> 0 | D133: =D134-D132 -> #REF! | E133: =E134-E132 -> #REF! | F133: =F134-F132 -> #REF! | G133: =G134-G132 -> #REF!
A134: LTD, End of Period | C134: =#REF! -> #REF! | D134: =#REF! -> #REF! | E134: =#REF! -> #REF! | F134: =#REF! -> #REF! | G134: =#REF! -> #REF!
A136: Long-Term Debt Interest (Average Debt) | C136: =#REF! -> #REF! | D136: =#REF! -> #REF! | E136: =#REF! -> #REF! | F136: =#REF! -> #REF! | G136: =#REF! -> #REF!
A138: Long Term Debt Interest | C138: =-C15 -> 12000 | D138: =-D15 -> 12000 | E138: =-E15 -> 12000 | F138: =F134*F136 -> #REF! | G138: =G134*G136 -> #REF!
A139: Total Interest | C139: =SUM(C138) -> 12000 | D139: =SUM(D138) -> 12000 | E139: =SUM(E138) -> 12000 | F139: =SUM(F138) -> #REF! | G139: =SUM(G138) -> #REF!
A141: Common Stock and Additional Paid-In Capital
A142: Beginning of Period | C142: =C144-C143 -> #REF! | D142: =C144 -> #REF! | E142: =D144 -> #REF! | F142: =E144 -> #REF! | G142: =F144 -> #REF!
A143: Additions (Repayments) | C143: =C77 -> 0 | D143: =D144-D142 -> #REF! | E143: =E144-E142 -> #REF! | F143: =F144-F142 -> #REF! | G143: =G144-G142 -> #REF!
A144: Common Stock, End of Period | C144: =#REF! -> #REF! | D144: =#REF! -> #REF! | E144: =#REF! -> #REF! | F144: =#REF! -> #REF! | G144: =#REF! -> #REF!
A146: Net Income | C146: =C19 -> 113629.62 | D146: =D19 -> 133358.16 | E146: =E19 -> 237355.56 | F146: =F19 -> 271202.88 | G146: =G19 -> 329558.58
...
