Workbook

Sheet README
A1: PT ABC Energy – Hulu RJPP 2026–2030 (Middle Scenario) – README
A2: Item | B2: Details
A3: Purpose | B3: Knowledge source for the Microsoft 365 Copilot agent "3C - RJPP Analyst" (SPPU SPARK Copilot training). All figures are dummy data for training only.
A4: Company | B4: PT ABC Energy
A5: Plan | B5: RJPP (Rencana Jangka Panjang Perusahaan – company long-term plan) 2026–2030
A6: Business line | B6: Hulu (Upstream Oil & Gas)
A7: Scenario | B7: Middle
A8: Currency & units | B8: Financial figures are in USD thousands. Operational units are stated on each row: oil production in MBOPD (thousand barrels of oil per day), gas production in MMSCFD (million standard cubic feet per day). Prices are stated per unit (USD/bbl, USD/MMBtu, USD/MMScf); the exchange rate is in IDR per USD.
A9: Revenue method | B9: Revenues (USD thousands) = (Total Produksi Minyak [MBOPD] × 1000 × 365 × Oil Price [USD/bbl] + Total Produksi Gas [MMSCFD] × 365 × Natural Gas Price [USD/MMScf]) / 1000.
A10: Color legend | B10: Blue font = input value; black font = formula; green font = live link to another sheet. Bold rows on a light-green fill are totals and key lines.
A11: Source | B11: Refined from 4_BL_Hulu_RJPP_2026_2030_MiddleScenario_ABCEnergy_v1.xlsx
A12: Sheet map
A13: Sheet: README | B13: This sheet – purpose, scope, units, sheet map and change log.
A14: Sheet: Key Assumptions | B14: Price and macro inputs by year (2026–2030): Oil Price (USD/bbl), Natural Gas Price (USD/MMBtu and USD/MMScf), Exchange rate USD/IDR (IDR per USD).
A15: Sheet: Operasional | B15: Oil production (MBOPD) and gas production (MMSCFD) by source – Produksi Domestik, Produksi Internasional, Produksi dari M&A – with group totals, 2026–2030.
A16: Sheet: Finansial | B16: Corporate tax rate input; income statement 2026–2030 in USD thousands (Revenues → Net Income, EBITDA margin, Net margin); Capital Expenditure (CAPEX) block.
A17: Sheet: Data | B17: Flat Excel Table "Data_Hulu": one row per metric of Key Assumptions, Operasional and Finansial (Business Line | Sheet | Section | Metric | Unit | 2026–2030), linked live to the source cells – for scripts and search.
A18: Changes from the source file
A19: Change 1 | B19: Fixed the unit typo "USD/MMSBtu" → "USD/MMBtu".
A20: Change 2 | B20: Removed the "Alternative Forecasting Methods" helper rows above the income statement and re-aligned the year columns.
A21: Change 3 | B21: Totals, subtotals and revenue are now live formulas.
A22: Change 4 | B22: The balance sheet and cash-flow sections of the source were removed because they contained broken references (#REF!) and template placeholder values.
A23: Data notes / to confirm
A24: Data notes | B24: None.

Sheet Key Assumptions
A1: PT ABC Energy – Hulu RJPP 2026–2030 (Middle Scenario) – Key Assumptions
A2: Parameter | B2: Unit | C2: 2026 | D2: 2027 | E2: 2028 | F2: 2029 | G2: 2030
A3: Oil Price | B3: USD/bbl | C3: 70 | D3: 75 | E3: 80 | F3: 85 | G3: 90
A4: Natural Gas Price | B4: USD/MMBtu | C4: 2.8 | D4: 2.85 | E4: 2.9 | F4: 2.95 | G4: 3
A5: Natural Gas Price | B5: USD/MMScf | C5: 2800 | D5: 2850 | E5: 2900 | F5: 2950 | G5: 3000
A6: Exchange rate USD/IDR | B6: IDR per USD | C6: 16500 | D6: 17000 | E6: 17500 | F6: 18000 | G6: 18500

Sheet Operasional
A1: PT ABC Energy – Hulu RJPP 2026–2030 (Middle Scenario) – Operasional (Production)
A2: Metric | B2: Unit | C2: 2026 | D2: 2027 | E2: 2028 | F2: 2029 | G2: 2030
A3: Oil production (Produksi Minyak)
A4: Produksi Domestik | B4: MBOPD | C4: 225 | D4: 215 | E4: 205 | F4: 190 | G4: 185
A5: Produksi Internasional | B5: MBOPD | C5: 90 | D5: 95 | E5: 100 | F5: 105 | G5: 110
A6: Produksi dari M&A | B6: MBOPD | C6: 0 | D6: 40 | E6: 70 | F6: 100 | G6: 150
A7: Total Produksi Minyak | B7: MBOPD | C7: =SUM(C4:C6) -> 315 | D7: =SUM(D4:D6) -> 350 | E7: =SUM(E4:E6) -> 375 | F7: =SUM(F4:F6) -> 395 | G7: =SUM(G4:G6) -> 445
A9: Gas production (Produksi Gas)
A10: Produksi Domestik | B10: MMSCFD | C10: 575 | D10: 625 | E10: 700 | F10: 750 | G10: 775
A11: Produksi Internasional | B11: MMSCFD | C11: 220 | D11: 230 | E11: 250 | F11: 275 | G11: 300
A12: Produksi dari M&A | B12: MMSCFD | C12: 0 | D12: 57 | E12: 150 | F12: 200 | G12: 250
A13: Total Produksi Gas | B13: MMSCFD | C13: =SUM(C10:C12) -> 795 | D13: =SUM(D10:D12) -> 912 | E13: =SUM(E10:E12) -> 1100 | F13: =SUM(F10:F12) -> 1225 | G13: =SUM(G10:G12) -> 1325

Sheet Finansial
A1: PT ABC Energy – Hulu RJPP 2026–2030 (Middle Scenario) – Finansial (Income Statement, USD thousands)
A2: Parameter | B2: Unit | C2: Value
A3: Corporate tax rate | B3: % | C3: 0.22
A5: Line item | B5: Unit | C5: 2026 | D5: 2027 | E5: 2028 | F5: 2029 | G5: 2030
A6: Income Statement
A7: Revenues | B7: USD thousands | C7: =(Operasional!C7*1000*365*'Key Assumptions'!C3+Operasional!C13*365*'Key Assumptions'!C5)/1000 -> 8860740 | D7: =(Operasional!D7*1000*365*'Key Assumptions'!D3+Operasional!D13*365*'Key Assumptions'!D5)/1000 -> 10529958 | E7: =(Operasional!E7*1000*365*'Key Assumptions'!E3+Operasional!E13*365*'Key Assumptions'!E5)/1000 -> 12114350 | F7: =(Operasional!F7*1000*365*'Key Assumptions'!F3+Operasional!F13*365*'Key Assumptions'!F5)/1000 -> 13573894 | G7: =(Operasional!G7*1000*365*'Key Assumptions'!G3+Operasional!G13*365*'Key Assumptions'!G5)/1000 -> 16069125
A8: Cost of Goods Sold | B8: USD thousands | C8: -4000000 | D8: -5000000 | E8: -6000000 | F8: -7000000 | G8: -8400000
A9: Gross Profit | B9: USD thousands | C9: =C7+C8 -> 4860740 | D9: =D7+D8 -> 5529958 | E9: =E7+E8 -> 6114350 | F9: =F7+F8 -> 6573893.8 | G9: =G7+G8 -> 7669125
A10: SG&A | B10: USD thousands | C10: -1350000 | D10: -1687500 | E10: -1968750 | F10: -2193750 | G10: -2475000
A11: EBITDA | B11: USD thousands | C11: =C9+C10 -> 3510740 | D11: =D9+D10 -> 3842458 | E11: =E9+E10 -> 4145600 | F11: =F9+F10 -> 4380143.8 | G11: =G9+G10 -> 5194125
A12: DD&A | B12: USD thousands | C12: -1000000 | D12: -1150000 | E12: -1300000 | F12: -1500000 | G12: -1750000
A13: EBIT (Operating Profit) | B13: USD thousands | C13: =C11+C12 -> 2510740 | D13: =D11+D12 -> 2692458 | E13: =E11+E12 -> 2845600 | F13: =F11+F12 -> 2880143.8 | G13: =G11+G12 -> 3444125
A14: Interest Expense | B14: USD thousands | C14: -150000 | D14: -175000 | E14: -200000 | F14: -225000 | G14: -250000
A15: Earnings Before Taxes | B15: USD thousands | C15: =C13+C14 -> 2360740 | D15: =D13+D14 -> 2517458 | E15: =E13+E14 -> 2645600 | F15: =F13+F14 -> 2655143.8 | G15: =G13+G14 -> 3194125
A16: Taxes | B16: USD thousands | C16: =-C15*$C$3 -> -519362.8 | D16: =-D15*$C$3 -> -553840.76 | E16: =-E15*$C$3 -> -582032 | F16: =-F15*$C$3 -> -584131.62 | G16: =-G15*$C$3 -> -702707.5
A17: Net Income | B17: USD thousands | C17: =C15+C16 -> 1841377.2 | D17: =D15+D16 -> 1963617.2 | E17: =E15+E16 -> 2063568 | F17: =F15+F16 -> 2071012.1 | G17: =G15+G16 -> 2491417.5
A18: EBITDA margin | B18: % | C18: =IF(C7=0,0,C11/C7) -> 0.39621296 | D18: =IF(D7=0,0,D11/D7) -> 0.36490725 | E18: =IF(E7=0,0,E11/E7) -> 0.34220573 | F18: =IF(F7=0,0,F11/F7) -> 0.32268882 | G18: =IF(G7=0,0,G11/G7) -> 0.32323633
A19: Net margin | B19: % | C19: =IF(C7=0,0,C17/C7) -> 0.20781303 | D19: =IF(D7=0,0,D17/D7) -> 0.18647911 | E19: =IF(E7=0,0,E17/E7) -> 0.17034079 | F19: =IF(F7=0,0,F17/F7) -> 0.15257318 | G19: =IF(G7=0,0,G17/G7) -> 0.15504376
A21: Capital Expenditure
A22: CAPEX | B22: USD thousands | C22: 3800000 | D22: 4600000 | E22: 5550000 | F22: 6400000 | G22: 7250000

Sheet Data
A1: PT ABC Energy – Hulu RJPP 2026–2030 (Middle Scenario) – Data (flat table Data_Hulu)
A2: Business Line | B2: Sheet | C2: Section | D2: Metric | E2: Unit | F2: 2026 | G2: 2027 | H2: 2028 | I2: 2029 | J2: 2030
A3: Hulu | B3: Key Assumptions | C3: Key Assumptions | D3: Oil Price | E3: USD/bbl | F3: ='Key Assumptions'!C3 -> 70 | G3: ='Key Assumptions'!D3 -> 75 | H3: ='Key Assumptions'!E3 -> 80 | I3: ='Key Assumptions'!F3 -> 85 | J3: ='Key Assumptions'!G3 -> 90
A4: Hulu | B4: Key Assumptions | C4: Key Assumptions | D4: Natural Gas Price | E4: USD/MMBtu | F4: ='Key Assumptions'!C4 -> 2.8 | G4: ='Key Assumptions'!D4 -> 2.85 | H4: ='Key Assumptions'!E4 -> 2.9 | I4: ='Key Assumptions'!F4 -> 2.95 | J4: ='Key Assumptions'!G4 -> 3
A5: Hulu | B5: Key Assumptions | C5: Key Assumptions | D5: Natural Gas Price | E5: USD/MMScf | F5: ='Key Assumptions'!C5 -> 2800 | G5: ='Key Assumptions'!D5 -> 2850 | H5: ='Key Assumptions'!E5 -> 2900 | I5: ='Key Assumptions'!F5 -> 2950 | J5: ='Key Assumptions'!G5 -> 3000
A6: Hulu | B6: Key Assumptions | C6: Key Assumptions | D6: Exchange rate USD/IDR | E6: IDR per USD | F6: ='Key Assumptions'!C6 -> 16500 | G6: ='Key Assumptions'!D6 -> 17000 | H6: ='Key Assumptions'!E6 -> 17500 | I6: ='Key Assumptions'!F6 -> 18000 | J6: ='Key Assumptions'!G6 -> 18500
A7: Hulu | B7: Operasional | C7: Oil production (Produksi Minyak) | D7: Produksi Domestik | E7: MBOPD | F7: =Operasional!C4 -> 225 | G7: =Operasional!D4 -> 215 | H7: =Operasional!E4 -> 205 | I7: =Operasional!F4 -> 190 | J7: =Operasional!G4 -> 185
A8: Hulu | B8: Operasional | C8: Oil production (Produksi Minyak) | D8: Produksi Internasional | E8: MBOPD | F8: =Operasional!C5 -> 90 | G8: =Operasional!D5 -> 95 | H8: =Operasional!E5 -> 100 | I8: =Operasional!F5 -> 105 | J8: =Operasional!G5 -> 110
A9: Hulu | B9: Operasional | C9: Oil production (Produksi Minyak) | D9: Produksi dari M&A | E9: MBOPD | F9: =Operasional!C6 -> 0 | G9: =Operasional!D6 -> 40 | H9: =Operasional!E6 -> 70 | I9: =Operasional!F6 -> 100 | J9: =Operasional!G6 -> 150
A10: Hulu | B10: Operasional | C10: Oil production (Produksi Minyak) | D10: Total Produksi Minyak | E10: MBOPD | F10: =Operasional!C7 -> 315 | G10: =Operasional!D7 -> 350 | H10: =Operasional!E7 -> 375 | I10: =Operasional!F7 -> 395 | J10: =Operasional!G7 -> 445
A11: Hulu | B11: Operasional | C11: Gas production (Produksi Gas) | D11: Produksi Domestik | E11: MMSCFD | F11: =Operasional!C10 -> 575 | G11: =Operasional!D10 -> 625 | H11: =Operasional!E10 -> 700 | I11: =Operasional!F10 -> 750 | J11: =Operasional!G10 -> 775
A12: Hulu | B12: Operasional | C12: Gas production (Produksi Gas) | D12: Produksi Internasional | E12: MMSCFD | F12: =Operasional!C11 -> 220 | G12: =Operasional!D11 -> 230 | H12: =Operasional!E11 -> 250 | I12: =Operasional!F11 -> 275 | J12: =Operasional!G11 -> 300
A13: Hulu | B13: Operasional | C13: Gas production (Produksi Gas) | D13: Produksi dari M&A | E13: MMSCFD | F13: =Operasional!C12 -> 0 | G13: =Operasional!D12 -> 57 | H13: =Operasional!E12 -> 150 | I13: =Operasional!F12 -> 200 | J13: =Operasional!G12 -> 250
A14: Hulu | B14: Operasional | C14: Gas production (Produksi Gas) | D14: Total Produksi Gas | E14: MMSCFD | F14: =Operasional!C13 -> 795 | G14: =Operasional!D13 -> 912 | H14: =Operasional!E13 -> 1100 | I14: =Operasional!F13 -> 1225 | J14: =Operasional!G13 -> 1325
A15: Hulu | B15: Finansial | C15: Assumptions | D15: Corporate tax rate | E15: % | F15: =Finansial!$C$3 -> 0.22 | G15: =Finansial!$C$3 -> 0.22 | H15: =Finansial!$C$3 -> 0.22 | I15: =Finansial!$C$3 -> 0.22 | J15: =Finansial!$C$3 -> 0.22
A16: Hulu | B16: Finansial | C16: Income Statement | D16: Revenues | E16: USD thousands | F16: =Finansial!C7 -> 8860740 | G16: =Finansial!D7 -> 10529958 | H16: =Finansial!E7 -> 12114350 | I16: =Finansial!F7 -> 13573894 | J16: =Finansial!G7 -> 16069125
A17: Hulu | B17: Finansial | C17: Income Statement | D17: Cost of Goods Sold | E17: USD thousands | F17: =Finansial!C8 -> -4000000 | G17: =Finansial!D8 -> -5000000 | H17: =Finansial!E8 -> -6000000 | I17: =Finansial!F8 -> -7000000 | J17: =Finansial!G8 -> -8400000
A18: Hulu | B18: Finansial | C18: Income Statement | D18: Gross Profit | E18: USD thousands | F18: =Finansial!C9 -> 4860740 | G18: =Finansial!D9 -> 5529958 | H18: =Finansial!E9 -> 6114350 | I18: =Finansial!F9 -> 6573893.8 | J18: =Finansial!G9 -> 7669125
A19: Hulu | B19: Finansial | C19: Income Statement | D19: SG&A | E19: USD thousands | F19: =Finansial!C10 -> -1350000 | G19: =Finansial!D10 -> -1687500 | H19: =Finansial!E10 -> -1968750 | I19: =Finansial!F10 -> -2193750 | J19: =Finansial!G10 -> -2475000
A20: Hulu | B20: Finansial | C20: Income Statement | D20: EBITDA | E20: USD thousands | F20: =Finansial!C11 -> 3510740 | G20: =Finansial!D11 -> 3842458 | H20: =Finansial!E11 -> 4145600 | I20: =Finansial!F11 -> 4380143.8 | J20: =Finansial!G11 -> 5194125
A21: Hulu | B21: Finansial | C21: Income Statement | D21: DD&A | E21: USD thousands | F21: =Finansial!C12 -> -1000000 | G21: =Finansial!D12 -> -1150000 | H21: =Finansial!E12 -> -1300000 | I21: =Finansial!F12 -> -1500000 | J21: =Finansial!G12 -> -1750000
A22: Hulu | B22: Finansial | C22: Income Statement | D22: EBIT (Operating Profit) | E22: USD thousands | F22: =Finansial!C13 -> 2510740 | G22: =Finansial!D13 -> 2692458 | H22: =Finansial!E13 -> 2845600 | I22: =Finansial!F13 -> 2880143.8 | J22: =Finansial!G13 -> 3444125
A23: Hulu | B23: Finansial | C23: Income Statement | D23: Interest Expense | E23: USD thousands | F23: =Finansial!C14 -> -150000 | G23: =Finansial!D14 -> -175000 | H23: =Finansial!E14 -> -200000 | I23: =Finansial!F14 -> -225000 | J23: =Finansial!G14 -> -250000
A24: Hulu | B24: Finansial | C24: Income Statement | D24: Earnings Before Taxes | E24: USD thousands | F24: =Finansial!C15 -> 2360740 | G24: =Finansial!D15 -> 2517458 | H24: =Finansial!E15 -> 2645600 | I24: =Finansial!F15 -> 2655143.8 | J24: =Finansial!G15 -> 3194125
A25: Hulu | B25: Finansial | C25: Income Statement | D25: Taxes | E25: USD thousands | F25: =Finansial!C16 -> -519362.8 | G25: =Finansial!D16 -> -553840.76 | H25: =Finansial!E16 -> -582032 | I25: =Finansial!F16 -> -584131.62 | J25: =Finansial!G16 -> -702707.5
A26: Hulu | B26: Finansial | C26: Income Statement | D26: Net Income | E26: USD thousands | F26: =Finansial!C17 -> 1841377.2 | G26: =Finansial!D17 -> 1963617.2 | H26: =Finansial!E17 -> 2063568 | I26: =Finansial!F17 -> 2071012.1 | J26: =Finansial!G17 -> 2491417.5
A27: Hulu | B27: Finansial | C27: Income Statement | D27: EBITDA margin | E27: % | F27: =Finansial!C18 -> 0.39621296 | G27: =Finansial!D18 -> 0.36490725 | H27: =Finansial!E18 -> 0.34220573 | I27: =Finansial!F18 -> 0.32268882 | J27: =Finansial!G18 -> 0.32323633
A28: Hulu | B28: Finansial | C28: Income Statement | D28: Net margin | E28: % | F28: =Finansial!C19 -> 0.20781303 | G28: =Finansial!D19 -> 0.18647911 | H28: =Finansial!E19 -> 0.17034079 | I28: =Finansial!F19 -> 0.15257318 | J28: =Finansial!G19 -> 0.15504376
A29: Hulu | B29: Finansial | C29: Capital Expenditure | D29: CAPEX | E29: USD thousands | F29: =Finansial!C22 -> 3800000 | G29: =Finansial!D22 -> 4600000 | H29: =Finansial!E22 -> 5550000 | I29: =Finansial!F22 -> 6400000 | J29: =Finansial!G22 -> 7250000
