Workbook

Sheet README
A1: README — PT ABC Energy RJPP 2026–2030 · New Energy (Geothermal, Solar & Power) · Middle Scenario
A2: Workbook information
A3: Purpose: Knowledge source for the Microsoft 365 Copilot agent "3C - RJPP Analyst" (SPPU SPARK Copilot training). All figures are DUMMY training data, not real company figures.
A4: Company: PT ABC Energy
A5: Plan: RJPP 2026–2030 (Rencana Jangka Panjang Perusahaan = company long-term plan)
A6: Business line: New Energy (Geothermal, Solar & Power)
A7: Scenario: Middle
A8: Currency & units: Financials are in USD thousands. Operational units are stated per row (MW, GWh, kWh). Prices are stated per unit (Harga Listrik in USD/kWh; exchange rate in IDR per USD).
A9: Source: Refined from 4_BL_NewEnergy_RJPP_2026_2030_MiddleScenario_ABCEnergy_v1.xlsx
A10: Color legend: blue font = hardcoded input; black font = formula on the same sheet; green font = cross-sheet link; bold rows with light-green fill = totals and key results.
A11: Sheet map
A12: README: Purpose, scope, units, sheet map, change log and data notes for this workbook.
... A22: None.

Sheet Key Assumptions
A1: Key Assumptions — PT ABC Energy New Energy RJPP 2026–2030 (Middle Scenario)
A2: Parameter | B2: Unit | C2: 2026 | D2: 2027 | E2: 2028 | F2: 2029 | G2: 2030
A3: Harga Listrik (electricity price) | B3: USD/kWh | C3: 0.08 | D3: 0.082 | E3: 0.085 | F3: 0.087 | G3: 0.09
A4: Exchange rate USD/IDR | B4: IDR per USD | C4: 16500 | D4: 17000 | E4: 17500 | F4: 18000 | G4: 18500

Sheet Operasional
A1: Operasional — Installed Capacity & Power Production, New Energy RJPP 2026–2030 (Middle Scenario)
A2: Metric | B2: Unit | C2: 2026 | D2: 2027 | E2: 2028 | F2: 2029 | G2: 2030
A3: Installed capacity (Kapasitas Terpasang)
A4: Geothermal | B4: MW | C4: 880 | D4: 960 | E4: 1300 | F4: 1400 | G4: 1600
A5: PLTS (solar) | B5: MW | C5: 160 | D5: 280 | E5: 320 | F5: 480 | G5: 500
A6: PLTSa (waste-to-energy) | B6: MW | C6: 50 | D6: 50 | E6: 50 | F6: 50 | G6: 50
A7: Total Kapasitas Terpasang | B7: MW | C7: =SUM(C4:C6) -> 1090 | D7: =SUM(D4:D6) -> 1290 | E7: =SUM(E4:E6) -> 1670 | F7: =SUM(F4:F6) -> 1930 | G7: =SUM(G4:G6) -> 2150
A9: Power production (Produksi Listrik)
A10: Geothermal | B10: GWh | C10: 5280 | D10: 5760 | E10: 9100 | F10: 9800 | G10: 11200
A11: PLTS (solar) | B11: GWh | C11: 40 | D11: 70 | E11: 160 | F11: 240 | G11: 250
A12: Other New Energy | B12: GWh | C12: 7 | D12: 42 | E12: 43 | F12: 44 | G12: 45
A13: Total Produksi Listrik | B13: GWh | C13: =SUM(C10:C12) -> 5327 | D13: =SUM(D10:D12) -> 5872 | E13: =SUM(E10:E12) -> 9303 | F13: =SUM(F10:F12) -> 10084 | G13: =SUM(G10:G12) -> 11495
A14: Total Produksi Listrik (kWh) | B14: kWh | C14: =C13*1000*1000 -> 5327000000 | D14: =D13*1000*1000 -> 5872000000 | E14: =E13*1000*1000 -> 9303000000 | F14: =F13*1000*1000 -> 10084000000 | G14: =G13*1000*1000 -> 11495000000

Sheet Finansial
A1: Finansial — Income Statement & CAPEX, New Energy RJPP 2026–2030 (Middle Scenario, USD thousands)
A2: Assumption | B2: Unit | C2: Value
A3: Corporate tax rate | B3: % | C3: 0.22
A5: Line item | B5: Unit | C5: 2026 | D5: 2027 | E5: 2028 | F5: 2029 | G5: 2030
A6: Revenues | B6: USD thousands | C6: =Operasional!C14*'Key Assumptions'!C3/1000 -> 426160 | D6: =Operasional!D14*'Key Assumptions'!D3/1000 -> 481504 | E6: =Operasional!E14*'Key Assumptions'!E3/1000 -> 790755 | F6: =Operasional!F14*'Key Assumptions'!F3/1000 -> 877308 | G6: =Operasional!G14*'Key Assumptions'!G3/1000 -> 1034550
A7: Cost of Goods Sold (COGS) | B7: USD thousands | C7: -191772 | D7: -211862 | E7: -332117 | F7: -359696 | G7: -413820
A8: Gross Profit | B8: USD thousands | C8: =C6+C7 -> 234388 | D8: =D6+D7 -> 269642 | E8: =E6+E7 -> 458638 | F8: =F6+F7 -> 517612 | G8: =G6+G7 -> 620730
A9: SG&A | B9: USD thousands | C9: -34093 | D9: -38520 | E9: -63260 | F9: -70185 | G9: -82764
A10: EBITDA | B10: USD thousands | C10: =C8+C9 -> 200295 | D10: =D8+D9 -> 231122 | E10: =E8+E9 -> 395378 | F10: =F8+F9 -> 447427 | G10: =G8+G9 -> 537966
A11: DD&A | B11: USD thousands | C11: -42616 | D11: -48150 | E11: -79076 | F11: -87731 | G11: -103455
A12: EBIT (Operating Profit) | B12: USD thousands | C12: =C10+C11 -> 157679 | D12: =D10+D11 -> 182972 | E12: =E10+E11 -> 316302 | F12: =F10+F11 -> 359696 | G12: =G10+G11 -> 434511
A13: Interest Expense | B13: USD thousands | C13: -12000 | D13: -12000 | E13: -12000 | F13: -12000 | G13: -12000
A14: Earnings Before Taxes (EBT) | B14: USD thousands | C14: =C12+C13 -> 145679 | D14: =D12+D13 -> 170972 | E14: =E12+E13 -> 304302 | F14: =F12+F13 -> 347696 | G14: =G12+G13 -> 422511
A15: Taxes | B15: USD thousands | C15: =-C14*$C$3 -> -32049.38 | D15: =-D14*$C$3 -> -37613.84 | E15: =-E14*$C$3 -> -66946.44 | F15: =-F14*$C$3 -> -76493.12 | G15: =-G14*$C$3 -> -92952.42
A16: Net Income | B16: USD thousands | C16: =C14+C15 -> 113629.62 | D16: =D14+D15 -> 133358.16 | E16: =E14+E15 -> 237355.56 | F16: =F14+F15 -> 271202.88 | G16: =G14+G15 -> 329558.58
A17: EBITDA margin | B17: % | C17: =IF(C6=0,0,C10/C6) -> 0.46999953 | D17: =IF(D6=0,0,D10/D6) -> 0.48000017 | E17: =IF(E6=0,0,E10/E6) -> 0.50000063 | F17: =IF(F6=0,0,F10/F6) -> 0.50999991 | G17: =IF(G6=0,0,G10/G6) -> 0.52
A18: Net margin | B18: % | C18: =IF(C6=0,0,C16/C6) -> 0.26663605 | D18: =IF(D6=0,0,D16/D6) -> 0.27696169 | E18: =IF(E6=0,0,E16/E6) -> 0.30016321 | F18: =IF(F6=0,0,F16/F6) -> 0.30913075 | G18: =IF(G6=0,0,G16/G6) -> 0.31855259
A20: Capital Expenditure
A21: CAPEX | B21: USD thousands | C21: 150000 | D21: 230000 | E21: 450000 | F21: 550000 | G21: 700000

Sheet Data
A1: Data — all New Energy RJPP 2026–2030 metrics (Middle Scenario), one row per metric, linked to source sheets
A2: Business Line | B2: Sheet | C2: Section | D2: Metric | E2: Unit | F2: 2026 | G2: 2027 | H2: 2028 | I2: 2029 | J2: 2030
A3: New Energy | B3: Key Assumptions | C3: Key Assumptions | D3: Harga Listrik (electricity price) | E3: USD/kWh | F3: ='Key Assumptions'!C3 -> 0.08 | G3: ='Key Assumptions'!D3 -> 0.082 | H3: ='Key Assumptions'!E3 -> 0.085 | I3: ='Key Assumptions'!F3 -> 0.087 | J3: ='Key Assumptions'!G3 -> 0.09
A4: New Energy | B4: Key Assumptions | C4: Key Assumptions | D4: Exchange rate USD/IDR | E4: IDR per USD | F4: ='Key Assumptions'!C4 -> 16500 | G4: ='Key Assumptions'!D4 -> 17000 | H4: ='Key Assumptions'!E4 -> 17500 | I4: ='Key Assumptions'!F4 -> 18000 | J4: ='Key Assumptions'!G4 -> 18500
A5: New Energy | B5: Operasional | C5: Installed capacity (Kapasitas Terpasang) | D5: Geothermal | E5: MW | F5: =Operasional!C4 -> 880 | G5: =Operasional!D4 -> 960 | H5: =Operasional!E4 -> 1300 | I5: =Operasional!F4 -> 1400 | J5: =Operasional!G4 -> 1600
A6: New Energy | B6: Operasional | C6: Installed capacity (Kapasitas Terpasang) | D6: PLTS (solar) | E6: MW | F6: =Operasional!C5 -> 160 | G6: =Operasional!D5 -> 280 | H6: =Operasional!E5 -> 320 | I6: =Operasional!F5 -> 480 | J6: =Operasional!G5 -> 500
A7: New Energy | B7: Operasional | C7: Installed capacity (Kapasitas Terpasang) | D7: PLTSa (waste-to-energy) | E7: MW | F7: =Operasional!C6 -> 50 | G7: =Operasional!D6 -> 50 | H7: =Operasional!E6 -> 50 | I7: =Operasional!F6 -> 50 | J7: =Operasional!G6 -> 50
A8: New Energy | B8: Operasional | C8: Installed capacity (Kapasitas Terpasang) | D8: Total Kapasitas Terpasang | E8: MW | F8: =Operasional!C7 -> 1090 | G8: =Operasional!D7 -> 1290 | H8: =Operasional!E7 -> 1670 | I8: =Operasional!F7 -> 1930 | J8: =Operasional!G7 -> 2150
A9: New Energy | B9: Operasional | C9: Power production (Produksi Listrik) | D9: Geothermal | E9: GWh | F9: =Operasional!C10 -> 5280 | G9: =Operasional!D10 -> 5760 | H9: =Operasional!E10 -> 9100 | I9: =Operasional!F10 -> 9800 | J9: =Operasional!G10 -> 11200
A10: New Energy | B10: Operasional | C10: Power production (Produksi Listrik) | D10: PLTS (solar) | E10: GWh | F10: =Operasional!C11 -> 40 | G10: =Operasional!D11 -> 70 | H10: =Operasional!E11 -> 160 | I10: =Operasional!F11 -> 240 | J10: =Operasional!G11 -> 250
A11: New Energy | B11: Operasional | C11: Power production (Produksi Listrik) | D11: Other New Energy | E11: GWh | F11: =Operasional!C12 -> 7 | G11: =Operasional!D12 -> 42 | H11: =Operasional!E12 -> 43 | I11: =Operasional!F12 -> 44 | J11: =Operasional!G12 -> 45
A12: New Energy | B12: Operasional | C12: Power production (Produksi Listrik) | D12: Total Produksi Listrik | E12: GWh | F12: =Operasional!C13 -> 5327 | G12: =Operasional!D13 -> 5872 | H12: =Operasional!E13 -> 9303 | I12: =Operasional!F13 -> 10084 | J12: =Operasional!G13 -> 11495
A13: New Energy | B13: Operasional | C13: Power production (Produksi Listrik) | D13: Total Produksi Listrik (kWh) | E13: kWh | F13: =Operasional!C14 -> 5327000000 | G13: =Operasional!D14 -> 5872000000 | H13: =Operasional!E14 -> 9303000000 | I13: =Operasional!F14 -> 10084000000 | J13: =Operasional!G14 -> 11495000000
A14: New Energy | B14: Finansial | C14: Assumptions | D14: Corporate tax rate | E14: % | F14: =Finansial!$C$3 -> 0.22 | G14: =Finansial!$C$3 -> 0.22 | H14: =Finansial!$C$3 -> 0.22 | I14: =Finansial!$C$3 -> 0.22 | J14: =Finansial!$C$3 -> 0.22
A15: New Energy | B15: Finansial | C15: Income statement | D15: Revenues | E15: USD thousands | F15: =Finansial!C6 -> 426160 | G15: =Finansial!D6 -> 481504 | H15: =Finansial!E6 -> 790755 | I15: =Finansial!F6 -> 877308 | J15: =Finansial!G6 -> 1034550
A16: New Energy | B16: Finansial | C16: Income statement | D16: Cost of Goods Sold (COGS) | E16: USD thousands | F16: =Finansial!C7 -> -191772 | G16: =Finansial!D7 -> -211862 | H16: =Finansial!E7 -> -332117 | I16: =Finansial!F7 -> -359696 | J16: =Finansial!G7 -> -413820
A17: New Energy | B17: Finansial | C17: Income statement | D17: Gross Profit | E17: USD thousands | F17: =Finansial!C8 -> 234388 | G17: =Finansial!D8 -> 269642 | H17: =Finansial!E8 -> 458638 | I17: =Finansial!F8 -> 517612 | J17: =Finansial!G8 -> 620730
A18: New Energy | B18: Finansial | C18: Income statement | D18: SG&A | E18: USD thousands | F18: =Finansial!C9 -> -34093 | G18: =Finansial!D9 -> -38520 | H18: =Finansial!E9 -> -63260 | I18: =Finansial!F9 -> -70185 | J18: =Finansial!G9 -> -82764
A19: New Energy | B19: Finansial | C19: Income statement | D19: EBITDA | E19: USD thousands | F19: =Finansial!C10 -> 200295 | G19: =Finansial!D10 -> 231122 | H19: =Finansial!E10 -> 395378 | I19: =Finansial!F10 -> 447427 | J19: =Finansial!G10 -> 537966
A20: New Energy | B20: Finansial | C20: Income statement | D20: DD&A | E20: USD thousands | F20: =Finansial!C11 -> -42616 | G20: =Finansial!D11 -> -48150 | H20: =Finansial!E11 -> -79076 | I20: =Finansial!F11 -> -87731 | J20: =Finansial!G11 -> -103455
A21: New Energy | B21: Finansial | C21: Income statement | D21: EBIT (Operating Profit) | E21: USD thousands | F21: =Finansial!C12 -> 157679 | G21: =Finansial!D12 -> 182972 | H21: =Finansial!E12 -> 316302 | I21: =Finansial!F12 -> 359696 | J21: =Finansial!G12 -> 434511
A22: New Energy | B22: Finansial | C22: Income statement | D22: Interest Expense | E22: USD thousands | F22: =Finansial!C13 -> -12000 | G22: =Finansial!D13 -> -12000 | H22: =Finansial!E13 -> -12000 | I22: =Finansial!F13 -> -12000 | J22: =Finansial!G13 -> -12000
A23: New Energy | B23: Finansial | C23: Income statement | D23: Earnings Before Taxes (EBT) | E23: USD thousands | F23: =Finansial!C14 -> 145679 | G23: =Finansial!D14 -> 170972 | H23: =Finansial!E14 -> 304302 | I23: =Finansial!F14 -> 347696 | J23: =Finansial!G14 -> 422511
A24: New Energy | B24: Finansial | C24: Income statement | D24: Taxes | E24: USD thousands | F24: =Finansial!C15 -> -32049.38 | G24: =Finansial!D15 -> -37613.84 | H24: =Finansial!E15 -> -66946.44 | I24: =Finansial!F15 -> -76493.12 | J24: =Finansial!G15 -> -92952.42
A25: New Energy | B25: Finansial | C25: Income statement | D25: Net Income | E25: USD thousands | F25: =Finansial!C16 -> 113629.62 | G25: =Finansial!D16 -> 133358.16 | H25: =Finansial!E16 -> 237355.56 | I25: =Finansial!F16 -> 271202.88 | J25: =Finansial!G16 -> 329558.58
A26: New Energy | B26: Finansial | C26: Income statement | D26: EBITDA margin | E26: % | F26: =Finansial!C17 -> 0.46999953 | G26: =Finansial!D17 -> 0.48000017 | H26: =Finansial!E17 -> 0.50000063 | I26: =Finansial!F17 -> 0.50999991 | J26: =Finansial!G17 -> 0.52
A27: New Energy | B27: Finansial | C27: Income statement | D27: Net margin | E27: % | F27: =Finansial!C18 -> 0.26663605 | G27: =Finansial!D18 -> 0.27696169 | H27: =Finansial!E18 -> 0.30016321 | I27: =Finansial!F18 -> 0.30913075 | J27: =Finansial!G18 -> 0.31855259
A28: New Energy | B28: Finansial | C28: Capital Expenditure | D28: CAPEX | E28: USD thousands | F28: =Finansial!C21 -> 150000 | G28: =Finansial!D21 -> 230000 | H28: =Finansial!E21 -> 450000 | I28: =Finansial!F21 -> 550000 | J28: =Finansial!G21 -> 700000
