Workbook

Sheet README
A1: PT ABC Energy — RJPP 2026–2030, Middle Scenario — Gas & LNG (Gas Trading & LNG) — README
A2: About this workbook
A3: Purpose: Knowledge source for the Microsoft 365 Copilot agent "3C - RJPP Analyst" (SPPU SPARK Copilot training). Dummy data for training only — not real company figures.
A4: Company: PT ABC Energy
A5: Plan: RJPP 2026–2030 (Rencana Jangka Panjang Perusahaan = company long-term plan)
A6: Business line: Gas & LNG (Gas Trading & LNG)
A7: Scenario: Middle
A8: Currency & units: Financials are in USD thousands. Operational units are stated on each row (BBTUD, MMBTUD). Prices are per unit as stated (oil in USD/bbl, natural gas and LNG in USD/MMBtu); the exchange rate is in IDR per USD.
A9: Source: Refined from 4_BL_GasLNG_RJPP_2026_2030_MiddleScenario_ABCEnergy_v1.xlsx
A10: Color legend: blue font = input values; black font = formulas; green font = links pulling values from other sheets; bold rows with light-green fill = totals and key results.
A11: Sheet map
A12: README — this guide: purpose, scope, units, sheet map, change log and data notes.
... A22: None.

Sheet Key Assumptions
A1: Key Assumptions — RJPP 2026–2030, Middle Scenario — Gas & LNG
A2: Parameter | B2: Unit | C2: 2026 | D2: 2027 | E2: 2028 | F2: 2029 | G2: 2030
A3: Oil Price | B3: USD/bbl | C3: 70 | D3: 75 | E3: 80 | F3: 85 | G3: 90
A4: Harga Gas Bumi (natural gas price) | B4: USD/MMBtu | C4: 6.5 | D4: 6.8 | E4: 7.1 | F4: 7.4 | G4: 7.7
A5: Harga LNG (LNG price) | B5: USD/MMBtu | C5: 13 | D5: 13 | E5: 14 | F5: 15 | G5: 16
A6: Exchange rate USD/IDR | B6: IDR per USD | C6: 16500 | D6: 17000 | E6: 17500 | F6: 18000 | G6: 18500

Sheet Operasional
A1: Operasional — Gas Trading Volumes 2026–2030, Middle Scenario — Gas & LNG
A2: Metric | B2: Unit | C2: 2026 | D2: 2027 | E2: 2028 | F2: 2029 | G2: 2030
A3: Gas trading (Niaga Gas) — BBTUD
A4: Niaga Gas | B4: BBTUD | C4: 780 | D4: 870 | E4: 1000 | F4: 1150 | G4: 1250
A5: LNG Trading | B5: BBTUD | C5: 50 | D5: 100 | E5: 120 | F5: 140 | G5: 150
A6: Total Volume Niaga Gas (BBTUD) | B6: BBTUD | C6: =SUM(C4:C5) -> 830 | D6: =SUM(D4:D5) -> 970 | E6: =SUM(E4:E5) -> 1120 | F6: =SUM(F4:F5) -> 1290 | G6: =SUM(G4:G5) -> 1400
A8: Gas trading (Niaga Gas) — MMBTUD
A9: Niaga Gas | B9: MMBTUD | C9: =C4*1000 -> 780000 | D9: =D4*1000 -> 870000 | E9: =E4*1000 -> 1000000 | F9: =F4*1000 -> 1150000 | G9: =G4*1000 -> 1250000
A10: LNG Trading | B10: MMBTUD | C10: =C5*1000 -> 50000 | D10: =D5*1000 -> 100000 | E10: =E5*1000 -> 120000 | F10: =F5*1000 -> 140000 | G10: =G5*1000 -> 150000
A11: Total Volume Niaga Gas (MMBTUD) | B11: MMBTUD | C11: =SUM(C9:C10) -> 830000 | D11: =SUM(D9:D10) -> 970000 | E11: =SUM(E9:E10) -> 1120000 | F11: =SUM(F9:F10) -> 1290000 | G11: =SUM(G9:G10) -> 1400000

Sheet Finansial
A1: Finansial — Income Statement 2026–2030 (USD thousands), Middle Scenario — Gas & LNG
A2: Line item | B2: Unit | C2: 2026 | D2: 2027 | E2: 2028 | F2: 2029 | G2: 2030
A3: Assumptions
A4: Corporate tax rate (applies to all years) | B4: % | C4: 0.22
A6: Income statement (USD thousands)
A7: Revenues | B7: USD thousands | C7: =(Operasional!C9*'Key Assumptions'!C4+Operasional!C10*'Key Assumptions'!C5)*365/1000 -> 2087800 | D7: =(Operasional!D9*'Key Assumptions'!D4+Operasional!D10*'Key Assumptions'!D5)*365/1000 -> 2633840 | E7: =(Operasional!E9*'Key Assumptions'!E4+Operasional!E10*'Key Assumptions'!E5)*365/1000 -> 3204700 | F7: =(Operasional!F9*'Key Assumptions'!F4+Operasional!F10*'Key Assumptions'!F5)*365/1000 -> 3872650 | G7: =(Operasional!G9*'Key Assumptions'!G4+Operasional!G10*'Key Assumptions'!G5)*365/1000 -> 4389125
A8: Cost of Goods Sold | B8: USD thousands | C8: -1836000 | D8: -2299000 | E8: -2675000 | F8: -3007000 | G8: -3663000
A9: Gross Profit | B9: USD thousands | C9: =C7+C8 -> 251800 | D9: =D7+D8 -> 334840 | E9: =E7+E8 -> 529700 | F9: =F7+F8 -> 865650 | G9: =G7+G8 -> 726125
A10: SG&A | B10: USD thousands | C10: -83500 | D10: -97500 | E10: -110700 | F10: -121400 | G10: -148700
A11: EBITDA | B11: USD thousands | C11: =C9+C10 -> 168300 | D11: =D9+D10 -> 237340 | E11: =E9+E10 -> 419000 | F11: =F9+F10 -> 744250 | G11: =G9+G10 -> 577425
A12: DD&A | B12: USD thousands | C12: -31300 | D12: -39500 | E12: -46100 | F12: -52000 | G12: -63700
A13: EBIT (Operating Profit) | B13: USD thousands | C13: =C11+C12 -> 137000 | D13: =D11+D12 -> 197840 | E13: =E11+E12 -> 372900 | F13: =F11+F12 -> 692250 | G13: =G11+G12 -> 513725
A14: Interest Expense | B14: USD thousands | C14: -20000 | D14: -20000 | E14: -20000 | F14: -20000 | G14: -20000
A15: Earnings Before Taxes | B15: USD thousands | C15: =C13+C14 -> 117000 | D15: =D13+D14 -> 177840 | E15: =E13+E14 -> 352900 | F15: =F13+F14 -> 672250 | G15: =G13+G14 -> 493725
A16: Taxes | B16: USD thousands | C16: =-C15*$C$4 -> -25740 | D16: =-D15*$C$4 -> -39124.8 | E16: =-E15*$C$4 -> -77638 | F16: =-F15*$C$4 -> -147895 | G16: =-G15*$C$4 -> -108619.5
A17: Net Income | B17: USD thousands | C17: =C15+C16 -> 91260 | D17: =D15+D16 -> 138715.2 | E17: =E15+E16 -> 275262 | F17: =F15+F16 -> 524355 | G17: =G15+G16 -> 385105.5
A18: EBITDA margin | B18: % | C18: =IF(C7=0,0,C11/C7) -> 0.08061117 | D18: =IF(D7=0,0,D11/D7) -> 0.090111776 | E18: =IF(E7=0,0,E11/E7) -> 0.13074547 | F18: =IF(F7=0,0,F11/F7) -> 0.19218106 | G18: =IF(G7=0,0,G11/G7) -> 0.13155811
A19: Net margin | B19: % | C19: =IF(C7=0,0,C17/C7) -> 0.043711083 | D19: =IF(D7=0,0,D17/D7) -> 0.052666525 | E19: =IF(E7=0,0,E17/E7) -> 0.085893219 | F19: =IF(F7=0,0,F17/F7) -> 0.13539953 | G19: =IF(G7=0,0,G17/G7) -> 0.087740837
A21: Capital Expenditure (USD thousands)
A22: CAPEX | B22: USD thousands | C22: 180000 | D22: 220000 | E22: 260000 | F22: 300000 | G22: 360000

Sheet Data
A1: Data — Gas & LNG RJPP 2026–2030, Middle Scenario (flat table of every metric, linked to source cells)
A2: Business Line | B2: Sheet | C2: Section | D2: Metric | E2: Unit | F2: 2026 | G2: 2027 | H2: 2028 | I2: 2029 | J2: 2030
A3: Gas & LNG | B3: Key Assumptions | C3: Price & macro assumptions | D3: Oil Price | E3: USD/bbl | F3: ='Key Assumptions'!C3 -> 70 | G3: ='Key Assumptions'!D3 -> 75 | H3: ='Key Assumptions'!E3 -> 80 | I3: ='Key Assumptions'!F3 -> 85 | J3: ='Key Assumptions'!G3 -> 90
A4: Gas & LNG | B4: Key Assumptions | C4: Price & macro assumptions | D4: Harga Gas Bumi (natural gas price) | E4: USD/MMBtu | F4: ='Key Assumptions'!C4 -> 6.5 | G4: ='Key Assumptions'!D4 -> 6.8 | H4: ='Key Assumptions'!E4 -> 7.1 | I4: ='Key Assumptions'!F4 -> 7.4 | J4: ='Key Assumptions'!G4 -> 7.7
A5: Gas & LNG | B5: Key Assumptions | C5: Price & macro assumptions | D5: Harga LNG (LNG price) | E5: USD/MMBtu | F5: ='Key Assumptions'!C5 -> 13 | G5: ='Key Assumptions'!D5 -> 13 | H5: ='Key Assumptions'!E5 -> 14 | I5: ='Key Assumptions'!F5 -> 15 | J5: ='Key Assumptions'!G5 -> 16
A6: Gas & LNG | B6: Key Assumptions | C6: Price & macro assumptions | D6: Exchange rate USD/IDR | E6: IDR per USD | F6: ='Key Assumptions'!C6 -> 16500 | G6: ='Key Assumptions'!D6 -> 17000 | H6: ='Key Assumptions'!E6 -> 17500 | I6: ='Key Assumptions'!F6 -> 18000 | J6: ='Key Assumptions'!G6 -> 18500
A7: Gas & LNG | B7: Operasional | C7: Gas trading (Niaga Gas) — BBTUD | D7: Niaga Gas | E7: BBTUD | F7: =Operasional!C4 -> 780 | G7: =Operasional!D4 -> 870 | H7: =Operasional!E4 -> 1000 | I7: =Operasional!F4 -> 1150 | J7: =Operasional!G4 -> 1250
A8: Gas & LNG | B8: Operasional | C8: Gas trading (Niaga Gas) — BBTUD | D8: LNG Trading | E8: BBTUD | F8: =Operasional!C5 -> 50 | G8: =Operasional!D5 -> 100 | H8: =Operasional!E5 -> 120 | I8: =Operasional!F5 -> 140 | J8: =Operasional!G5 -> 150
A9: Gas & LNG | B9: Operasional | C9: Gas trading (Niaga Gas) — BBTUD | D9: Total Volume Niaga Gas (BBTUD) | E9: BBTUD | F9: =Operasional!C6 -> 830 | G9: =Operasional!D6 -> 970 | H9: =Operasional!E6 -> 1120 | I9: =Operasional!F6 -> 1290 | J9: =Operasional!G6 -> 1400
A10: Gas & LNG | B10: Operasional | C10: Gas trading (Niaga Gas) — MMBTUD | D10: Niaga Gas | E10: MMBTUD | F10: =Operasional!C9 -> 780000 | G10: =Operasional!D9 -> 870000 | H10: =Operasional!E9 -> 1000000 | I10: =Operasional!F9 -> 1150000 | J10: =Operasional!G9 -> 1250000
A11: Gas & LNG | B11: Operasional | C11: Gas trading (Niaga Gas) — MMBTUD | D11: LNG Trading | E11: MMBTUD | F11: =Operasional!C10 -> 50000 | G11: =Operasional!D10 -> 100000 | H11: =Operasional!E10 -> 120000 | I11: =Operasional!F10 -> 140000 | J11: =Operasional!G10 -> 150000
A12: Gas & LNG | B12: Operasional | C12: Gas trading (Niaga Gas) — MMBTUD | D12: Total Volume Niaga Gas (MMBTUD) | E12: MMBTUD | F12: =Operasional!C11 -> 830000 | G12: =Operasional!D11 -> 970000 | H12: =Operasional!E11 -> 1120000 | I12: =Operasional!F11 -> 1290000 | J12: =Operasional!G11 -> 1400000
A13: Gas & LNG | B13: Finansial | C13: Assumptions | D13: Corporate tax rate | E13: % | F13: =Finansial!$C$4 -> 0.22 | G13: =Finansial!$C$4 -> 0.22 | H13: =Finansial!$C$4 -> 0.22 | I13: =Finansial!$C$4 -> 0.22 | J13: =Finansial!$C$4 -> 0.22
A14: Gas & LNG | B14: Finansial | C14: Income statement | D14: Revenues | E14: USD thousands | F14: =Finansial!C7 -> 2087800 | G14: =Finansial!D7 -> 2633840 | H14: =Finansial!E7 -> 3204700 | I14: =Finansial!F7 -> 3872650 | J14: =Finansial!G7 -> 4389125
A15: Gas & LNG | B15: Finansial | C15: Income statement | D15: Cost of Goods Sold | E15: USD thousands | F15: =Finansial!C8 -> -1836000 | G15: =Finansial!D8 -> -2299000 | H15: =Finansial!E8 -> -2675000 | I15: =Finansial!F8 -> -3007000 | J15: =Finansial!G8 -> -3663000
A16: Gas & LNG | B16: Finansial | C16: Income statement | D16: Gross Profit | E16: USD thousands | F16: =Finansial!C9 -> 251800 | G16: =Finansial!D9 -> 334840 | H16: =Finansial!E9 -> 529700 | I16: =Finansial!F9 -> 865650 | J16: =Finansial!G9 -> 726125
A17: Gas & LNG | B17: Finansial | C17: Income statement | D17: SG&A | E17: USD thousands | F17: =Finansial!C10 -> -83500 | G17: =Finansial!D10 -> -97500 | H17: =Finansial!E10 -> -110700 | I17: =Finansial!F10 -> -121400 | J17: =Finansial!G10 -> -148700
A18: Gas & LNG | B18: Finansial | C18: Income statement | D18: EBITDA | E18: USD thousands | F18: =Finansial!C11 -> 168300 | G18: =Finansial!D11 -> 237340 | H18: =Finansial!E11 -> 419000 | I18: =Finansial!F11 -> 744250 | J18: =Finansial!G11 -> 577425
A19: Gas & LNG | B19: Finansial | C19: Income statement | D19: DD&A | E19: USD thousands | F19: =Finansial!C12 -> -31300 | G19: =Finansial!D12 -> -39500 | H19: =Finansial!E12 -> -46100 | I19: =Finansial!F12 -> -52000 | J19: =Finansial!G12 -> -63700
A20: Gas & LNG | B20: Finansial | C20: Income statement | D20: EBIT (Operating Profit) | E20: USD thousands | F20: =Finansial!C13 -> 137000 | G20: =Finansial!D13 -> 197840 | H20: =Finansial!E13 -> 372900 | I20: =Finansial!F13 -> 692250 | J20: =Finansial!G13 -> 513725
A21: Gas & LNG | B21: Finansial | C21: Income statement | D21: Interest Expense | E21: USD thousands | F21: =Finansial!C14 -> -20000 | G21: =Finansial!D14 -> -20000 | H21: =Finansial!E14 -> -20000 | I21: =Finansial!F14 -> -20000 | J21: =Finansial!G14 -> -20000
A22: Gas & LNG | B22: Finansial | C22: Income statement | D22: Earnings Before Taxes | E22: USD thousands | F22: =Finansial!C15 -> 117000 | G22: =Finansial!D15 -> 177840 | H22: =Finansial!E15 -> 352900 | I22: =Finansial!F15 -> 672250 | J22: =Finansial!G15 -> 493725
A23: Gas & LNG | B23: Finansial | C23: Income statement | D23: Taxes | E23: USD thousands | F23: =Finansial!C16 -> -25740 | G23: =Finansial!D16 -> -39124.8 | H23: =Finansial!E16 -> -77638 | I23: =Finansial!F16 -> -147895 | J23: =Finansial!G16 -> -108619.5
A24: Gas & LNG | B24: Finansial | C24: Income statement | D24: Net Income | E24: USD thousands | F24: =Finansial!C17 -> 91260 | G24: =Finansial!D17 -> 138715.2 | H24: =Finansial!E17 -> 275262 | I24: =Finansial!F17 -> 524355 | J24: =Finansial!G17 -> 385105.5
A25: Gas & LNG | B25: Finansial | C25: Income statement | D25: EBITDA margin | E25: % | F25: =Finansial!C18 -> 0.08061117 | G25: =Finansial!D18 -> 0.090111776 | H25: =Finansial!E18 -> 0.13074547 | I25: =Finansial!F18 -> 0.19218106 | J25: =Finansial!G18 -> 0.13155811
A26: Gas & LNG | B26: Finansial | C26: Income statement | D26: Net margin | E26: % | F26: =Finansial!C19 -> 0.043711083 | G26: =Finansial!D19 -> 0.052666525 | H26: =Finansial!E19 -> 0.085893219 | I26: =Finansial!F19 -> 0.13539953 | J26: =Finansial!G19 -> 0.087740837
A27: Gas & LNG | B27: Finansial | C27: Capital Expenditure | D27: CAPEX | E27: USD thousands | F27: =Finansial!C22 -> 180000 | G27: =Finansial!D22 -> 220000 | H27: =Finansial!E22 -> 260000 | I27: =Finansial!F22 -> 300000 | J27: =Finansial!G22 -> 360000
